restai_functions/__init__.py
restai_functions/restai.py
restai_functions-0.0.4.dist-info/LICENSE
restai_functions-0.0.4.dist-info/METADATA
restai_functions-0.0.4.dist-info/WHEEL
restai_functions-0.0.4.dist-info/RECORD
