Metadata-Version: 2.3
Name: restai-functions
Version: 0.0.4
Summary: Call RESTai projects using direct functions in Python
License: Apache-2.0
Author: Pedro Dias
Author-email: petermdias@gmail.com
Requires-Python: >=3.12
Classifier: Programming Language :: Python :: 3
Classifier: Operating System :: OS Independent
Requires-Dist: requests
Project-URL: Homepage, https://github.com/apocas/restai-functions
